jarjar/__init__.py
jarjar/_version.py
jarjar/jarjar.py
jarjar/screen.py
jarjar-3.2.data/scripts/jarjar
jarjar-3.2.dist-info/METADATA
jarjar-3.2.dist-info/WHEEL
jarjar-3.2.dist-info/top_level.txt
jarjar-3.2.dist-info/RECORD
